{
  "status": "pending",
  "idea": {
    "id": "idea-1773352217-9",
    "title": "Social Media Ad Copy Variations Toolkit",
    "description": "40 prompts for paid media managers to generate multiple headline, body copy, and CTA variations for Facebook and Instagram ads across different buyer awareness stages.",
    "category": "prompt-packs",
    "tags": [
      "paid ads",
      "copywriting",
      "social media"
    ],
    "score": 91,
    "rationale": "Paid media managers face constant pressure to produce copy variations at scale, the audience is large and monetarily motivated, and AI excels at generating structured ad copy across awareness stages with high consistency.",
    "selected": true,
    "status": null,
    "product_id": null,
    "generated_at": "2026-03-12T21:50:17.291121+00:00",
    "source": "trend-scan"
  },
  "requested_at": "2026-03-12T21:51:14.427721+00:00",
  "decided_at": null
}
